CFPy/__init__.py
CFPy/cfp/__init__.py
CFPy/cfp/cfp.py
CFPy/cfp/coc.py
CFPy/cfp/crch.py
CFPy/cfp/soc.py
CFPy/cfp/stm.py
CFPy/cfp/write_input.py
CFPy/utils/__init__.py
CFPy/utils/nbr.py
CFPy/utils/plots.py
CFPy/utils/postprocessing.py
CFPy/utils/preprocessing.py
CFPy/utils/update_nam.py
CFPy_TUD-0.0.2.dist-info/LICENSE
CFPy_TUD-0.0.2.dist-info/METADATA
CFPy_TUD-0.0.2.dist-info/WHEEL
CFPy_TUD-0.0.2.dist-info/top_level.txt
CFPy_TUD-0.0.2.dist-info/RECORD
